triclick_doc_toolset/__init__.py
triclick_doc_toolset/service.py
triclick_doc_toolset/commands/__init__.py
triclick_doc_toolset/commands/docx_file_parse_cmd.py
triclick_doc_toolset/commands/docx_file_partition_cmd.py
triclick_doc_toolset/commands/enhance_level_cmd.py
triclick_doc_toolset/commands/enhance_tree_cmd.py
triclick_doc_toolset/commands/file_type_identify_cmd.py
triclick_doc_toolset/commands/rtf_file_parse_cmd.py
triclick_doc_toolset/commands/rtf_file_partition_cmd.py
triclick_doc_toolset/common/__init__.py
triclick_doc_toolset/common/models/__init__.py
triclick_doc_toolset/common/models/table.py
triclick_doc_toolset/common/rtf/__init__.py
triclick_doc_toolset/common/rtf/rtf_file_parse_util.py
triclick_doc_toolset/common/rtf/rtf_file_partition_util.py
triclick_doc_toolset/common/rtf/rtf_text_util.py
triclick_doc_toolset/common/rules/__init__.py
triclick_doc_toolset/common/rules/normalize_duplicate_labels_rule.py
triclick_doc_toolset/common/rules/same_as_rule.py
triclick_doc_toolset/common/utils/__init__.py
triclick_doc_toolset/common/utils/text_utils.py
triclick_doc_toolset/common/utils/yaml_utils.py
triclick_doc_toolset/common/word/__init__.py
triclick_doc_toolset/common/word/docx_file_parse_util.py
triclick_doc_toolset/common/word/docx_file_partition_util.py
triclick_doc_toolset/common/word/title_util.py
triclick_doc_toolset/framework/__init__.py
triclick_doc_toolset/framework/command.py
triclick_doc_toolset/framework/command_registry.py
triclick_doc_toolset/framework/context.py
triclick_doc_toolset/framework/pipeline.py
triclick_doc_toolset/framework/strategy.py
triclick_doc_toolset/toolset/__init__.py
triclick_doc_toolset/toolset/excel_utility.py
triclick_doc_toolset/toolset/gen_tlf_header_excel.py
triclick_doc_toolset/resources/pipelines/generation.yaml
triclick_doc_toolset/resources/pipelines/review.yaml
triclick_doc_toolset/resources/pipelines/title_table_footnote_patterns.yaml
triclick_doc_toolset/resources/templates/TLF_TOC_heading_template.xlsx
triclick_doc_toolset-1.5.4.dist-info/METADATA
triclick_doc_toolset-1.5.4.dist-info/WHEEL
triclick_doc_toolset-1.5.4.dist-info/RECORD
