Metadata-Version: 2.4
Name: triclick-doc-toolset
Version: 1.5.4
Summary: Advanced document partitioning and processing toolset
Requires-Python: >=3.10
Requires-Dist: openpyxl>=3.1.5
Requires-Dist: pandas>=2.0.0
Requires-Dist: pydantic>=2.12.5
Requires-Dist: python-docx>=1.2.0
Requires-Dist: pyyaml>=6.0
Provides-Extra: dev
Requires-Dist: pytest>=9.0.1; extra == 'dev'
